setup.py
rManifolds/__init__.py
rManifolds/gaussian_walk.py
rManifolds/rBraid.py
rManifolds/rUnifKnot.py
rManifolds.egg-info/PKG-INFO
rManifolds.egg-info/SOURCES.txt
rManifolds.egg-info/dependency_links.txt
rManifolds.egg-info/not-zip-safe
rManifolds.egg-info/top_level.txt