Metadata-Version: 1.0
Name: rManifolds
Version: 0.1
Summary: Manifolds in snappy from random knots/links/braids
Home-page: http://github.com/mauriciogtec/rManifolds
Author: Mauricio B. Garcia Tec
Author-email: UNKNOWN
License: MIT
Platform: UNKNOWN
